teamgenerator/__init__.py
teamgenerator-1.0.dist-info/WHEEL
teamgenerator-1.0.dist-info/METADATA
teamgenerator-1.0.dist-info/RECORD
